{"stats":{"minecraft:broken":{"minecraft:iron_pickaxe":2},"minecraft:crafted":{"minecraft:oak_planks":44,"minecraft:cooked_chicken":7,"minecraft:furnace":4,"minecraft:cooked_mutton":2,"minecraft:flint_and_steel":1,"minecraft:iron_boots":1,"minecraft:stone_pickaxe":3,"minecraft:chest":1,"minecraft:golden_boots":1,"minecraft:wheat":63,"minecraft:cooked_beef":2,"minecraft:diamond_sword":1,"minecraft:crafting_table":5,"minecraft:wooden_pickaxe":2,"minecraft:iron_helmet":1,"minecraft:iron_sword":1,"minecraft:cooked_salmon":5,"minecraft:bucket":1,"minecraft:stone_axe":3,"minecraft:bread":21,"minecraft:acacia_boat":2,"minecraft:iron_chestplate":1,"minecraft:diamond_pickaxe":1,"minecraft:shield":1,"minecraft:stick":8,"minecraft:iron_ingot":45,"minecraft:iron_pickaxe":2,"minecraft:stone_sword":1,"minecraft:iron_leggings":1,"minecraft:gold_ingot":6,"minecraft:acacia_planks":60},"minecraft:used":{"minecraft:stone_sword":7,"minecraft:flint_and_steel":1,"minecraft:chest":3,"minecraft:shield":1,"minecraft:iron_sword":49,"minecraft:cooked_salmon":1,"minecraft:cooked_chicken":4,"minecraft:netherrack":48,"minecraft:torch":1,"minecraft:dirt":4,"minecraft:tuff":13,"minecraft:obsidian":10,"minecraft:iron_helmet":1,"minecraft:iron_boots":1,"minecraft:bow":1,"minecraft:furnace":6,"minecraft:egg":1,"minecraft:cooked_beef":2,"minecraft:cobbled_deepslate":117,"minecraft:iron_leggings":1,"minecraft:golden_boots":1,"minecraft:acacia_boat":3,"minecraft:water_bucket":2,"minecraft:stone_pickaxe":214,"minecraft:wooden_pickaxe":9,"minecraft:sand":2,"minecraft:crafting_table":13,"minecraft:blast_furnace":1,"minecraft:diamond_pickaxe":155,"minecraft:apple":1,"minecraft:bread":6,"minecraft:cyan_bed":5,"minecraft:iron_pickaxe":500,"minecraft:stone_axe":106,"minecraft:diamond_sword":8,"minecraft:cobblestone":86,"minecraft:bucket":2},"minecraft:mined":{"minecraft:nether_gold_ore":18,"minecraft:tuff":38,"minecraft:deepslate_diamond_ore":27,"minecraft:brewing_stand":1,"minecraft:obsidian":14,"minecraft:granite":8,"minecraft:acacia_log":24,"minecraft:grass_block":4,"minecraft:cracked_polished_blackstone_bricks":2,"minecraft:sandstone":1,"minecraft:hay_block":65,"minecraft:polished_blackstone_bricks":11,"minecraft:tall_seagrass":1,"minecraft:furnace":4,"minecraft:iron_ore":56,"minecraft:fire":24,"minecraft:acacia_wood":2,"minecraft:andesite":13,"minecraft:potted_dandelion":1,"minecraft:deepslate_iron_ore":2,"minecraft:stone":233,"minecraft:acacia_leaves":1,"minecraft:blackstone":4,"minecraft:melon_stem":1,"minecraft:crafting_table":9,"minecraft:short_grass":22,"minecraft:blackstone_slab":6,"minecraft:chest":3,"minecraft:dead_bush":52,"minecraft:nether_quartz_ore":16,"minecraft:tall_grass":2,"minecraft:cobblestone":4,"minecraft:cyan_bed":6,"minecraft:lapis_ore":2,"minecraft:polished_blackstone_brick_stairs":2,"minecraft:sugar_cane":19,"minecraft:oak_planks":3,"minecraft:diorite":22,"minecraft:wall_torch":4,"minecraft:seagrass":3,"minecraft:white_terracotta":1,"minecraft:cactus":3,"minecraft:oak_log":46,"minecraft:coal_ore":67,"minecraft:gravel":20,"minecraft:sand":4,"minecraft:dirt":11,"minecraft:terracotta":1,"minecraft:netherrack":69,"minecraft:gold_ore":6,"minecraft:oak_leaves":6,"minecraft:deepslate":228},"minecraft:dropped":{"minecraft:iron_sword":1,"minecraft:granite":8,"minecraft:iron_pickaxe":1,"minecraft:gold_ingot":2,"minecraft:gravel":33,"minecraft:furnace":1,"minecraft:cooked_chicken":3,"minecraft:iron_boots":1,"minecraft:white_terracotta":1,"minecraft:wooden_pickaxe":1},"minecraft:killed_by":{"minecraft:husk":1,"minecraft:piglin_brute":1,"minecraft:piglin":1},"minecraft:picked_up":{"minecraft:crafting_table":10,"minecraft:chicken":7,"minecraft:wooden_pickaxe":1,"minecraft:brewing_stand":1,"minecraft:amethyst_block":12,"minecraft:string":3,"minecraft:polished_blackstone_brick_stairs":2,"minecraft:netherite_ingot":2,"minecraft:blackstone":2,"minecraft:gold_nugget":76,"minecraft:cobbled_deepslate":418,"minecraft:beef":2,"minecraft:calcite":11,"minecraft:iron_pickaxe":1,"minecraft:sugar_cane":33,"minecraft:chest":3,"minecraft:egg":1,"minecraft:furnace":5,"minecraft:sandstone":1,"minecraft:stick":73,"minecraft:raw_iron":60,"minecraft:torch":10,"minecraft:acacia_log":58,"minecraft:polished_blackstone_bricks":9,"minecraft:diorite":22,"minecraft:cactus":6,"minecraft:stone_shovel":1,"minecraft:hay_block":64,"minecraft:iron_block":1,"minecraft:white_terracotta":1,"minecraft:obsidian":14,"minecraft:cobblestone":364,"minecraft:andesite":13,"minecraft:salmon":5,"minecraft:leather":3,"minecraft:blackstone_slab":6,"minecraft:acacia_wood":2,"minecraft:flint":1,"minecraft:tuff":73,"minecraft:oak_log":46,"minecraft:acacia_boat":1,"minecraft:lapis_lazuli":13,"minecraft:dirt":15,"minecraft:bone":1,"minecraft:apple":1,"minecraft:bow":1,"minecraft:wheat_seeds":10,"minecraft:raw_gold":6,"minecraft:rabbit":2,"minecraft:iron_sword":1,"minecraft:oak_planks":7,"minecraft:quartz":16,"minecraft:gravel":57,"minecraft:sand":4,"minecraft:blast_furnace":1,"minecraft:cyan_bed":6,"minecraft:spider_eye":1,"minecraft:diamond":26,"minecraft:cracked_polished_blackstone_bricks":2,"minecraft:granite":32,"minecraft:terracotta":1,"minecraft:oak_sapling":2,"minecraft:melon_seeds":3,"minecraft:netherrack":65,"minecraft:coal":67},"minecraft:killed":{"minecraft:spider":2,"minecraft:phantom":1,"minecraft:piglin_brute":1,"minecraft:salmon":7,"minecraft:rabbit":1,"minecraft:zombie":1},"minecraft:custom":{"minecraft:mob_kills":14,"minecraft:interact_with_crafting_table":32,"minecraft:leave_game":12,"minecraft:time_since_death":424,"minecraft:climb_one_cm":424,"minecraft:sprint_one_cm":277139,"minecraft:walk_one_cm":496771,"minecraft:damage_blocked_by_shield":75,"minecraft:drop":12,"minecraft:play_time":154379,"minecraft:deaths":7,"minecraft:sneak_time":2567,"minecraft:walk_under_water_one_cm":24520,"minecraft:boat_one_cm":28478,"minecraft:jump":2168,"minecraft:interact_with_blast_furnace":3,"minecraft:walk_on_water_one_cm":43817,"minecraft:total_world_time":154379,"minecraft:interact_with_furnace":69,"minecraft:sleep_in_bed":10,"minecraft:time_since_rest":455,"minecraft:damage_taken":2162,"minecraft:damage_dealt":1888,"minecraft:swim_one_cm":39162,"minecraft:fly_one_cm":379027,"minecraft:open_chest":23,"minecraft:crouch_one_cm":4406,"minecraft:fall_one_cm":70982}},"DataVersion":3955}